sdn_test_simple_car/__init__.py
sdn_test_simple_car/simple_car.py
sdn_test_simple_car-0.1.0.dist-info/licenses/LICENSE
sdn_test_simple_car-0.1.0.dist-info/METADATA
sdn_test_simple_car-0.1.0.dist-info/WHEEL
sdn_test_simple_car-0.1.0.dist-info/top_level.txt
sdn_test_simple_car-0.1.0.dist-info/RECORD
